osparcAPIcontrol/__init__.py
osparcAPIcontrol/controller.py
osparcAPIcontrol-0.0.6.dist-info/LICENSE
osparcAPIcontrol-0.0.6.dist-info/METADATA
osparcAPIcontrol-0.0.6.dist-info/WHEEL
osparcAPIcontrol-0.0.6.dist-info/top_level.txt
osparcAPIcontrol-0.0.6.dist-info/RECORD
