Metadata-Version: 2.1
Name: osparcAPIcontrol
Version: 0.0.6
Summary: tools to interact with osparc API
Home-page: https://git.speag.com/msteiner/osparcapicontrol.git
Author: Konohana
Author-email: msteiner@itis.swiss
License: MIT
Keywords: OpenAPI,OpenAPI-Generator,osparc,web API
Platform: UNKNOWN
Classifier: Development Status :: 3 - Alpha
Classifier: License :: OSI Approved :: MIT License
Classifier: Programming Language :: Python :: 3
Classifier: Operating System :: OS Independent
Classifier: Natural Language :: English
License-File: LICENSE
Requires-Dist: osparc
Requires-Dist: tenacity
